EDAspy/__init__.py
EDAspy/benchmarks/__init__.py
EDAspy/benchmarks/binary.py
EDAspy/benchmarks/continuous.py
EDAspy/optimization/__init__.py
EDAspy/optimization/eda.py
EDAspy/optimization/eda_result.py
EDAspy/optimization/custom/__init__.py
EDAspy/optimization/custom/eda_custom.py
EDAspy/optimization/custom/initialization_models/__init__.py
EDAspy/optimization/custom/initialization_models/_generation_init.py
EDAspy/optimization/custom/initialization_models/multi_gauss_gininit.py
EDAspy/optimization/custom/initialization_models/uni_bin_geninit.py
EDAspy/optimization/custom/initialization_models/uni_gauss_geninit.py
EDAspy/optimization/custom/initialization_models/uniform_geninit.py
EDAspy/optimization/custom/probabilistic_models/__init__.py
EDAspy/optimization/custom/probabilistic_models/_probabilistic_model.py
EDAspy/optimization/custom/probabilistic_models/gaussian_bayesian_network.py
EDAspy/optimization/custom/probabilistic_models/multivariate_gaussian.py
EDAspy/optimization/custom/probabilistic_models/univariate_binary.py
EDAspy/optimization/custom/probabilistic_models/univariate_gaussian.py
EDAspy/optimization/multivariate/__init__.py
EDAspy/optimization/multivariate/egna.py
EDAspy/optimization/multivariate/emna.py
EDAspy/optimization/univariate/__init__.py
EDAspy/optimization/univariate/umda_binary.py
EDAspy/optimization/univariate/umda_continuous.py
EDAspy/timeseries/TS_transformations.py
EDAspy/timeseries/TransformationsFeatureSelection.py
EDAspy/timeseries/__init__.py
tests/__init__.py
tests/test_egna.py
tests/test_emna.py
tests/test_geninit.py
tests/test_umdac.py
tests/test_umdad.py
EDAspy-1.0.1.dist-info/LICENSE
EDAspy-1.0.1.dist-info/METADATA
EDAspy-1.0.1.dist-info/WHEEL
EDAspy-1.0.1.dist-info/top_level.txt
EDAspy-1.0.1.dist-info/RECORD
