Metadata-Version: 2.1
Name: EDAspy
Version: 1.0.1
Summary: EDAspy is a Python package that implements Estimation of Distribution Algorithms. EDAspy allows toeither use already existing implementations or customize the EDAs baseline easily building it bymodules so new research can be easily developed. It also has several benchmarks for comparisons.
Home-page: https://github.com/VicentePerezSoloviev/EDAspy
Author: Vicente P. Soloviev
Author-email: vicente.perez.soloviev@gmail.com
License: MIT
Download-URL: https://github.com/VicentePerezSoloviev/EDAspy/archive/1.0.0.tar.gz
Keywords: EDA,estimation,bayesian,evolutionary,algorithm,optimization,time_series,feature,selection,semiparametric,Gaussian
Platform: UNKNOWN
Classifier: Development Status :: 5 - Production/Stable
Classifier: Programming Language :: Python :: 3
Classifier: License :: OSI Approved :: MIT License
Classifier: Operating System :: OS Independent
Requires-Python: >=3.0
Requires-Dist: pandas (>=1.2.0)
Requires-Dist: numpy (>1.15.0)
Requires-Dist: pybnesian (>=0.3.4)
